bazis/contrib/users/__init__.py
bazis/contrib/users/_version.py
bazis/contrib/users/admin_abstract.py
bazis/contrib/users/apps.py
bazis/contrib/users/conf.py
bazis/contrib/users/middleware.py
bazis/contrib/users/models.py
bazis/contrib/users/models_abstract.py
bazis/contrib/users/router.py
bazis/contrib/users/routes.py
bazis/contrib/users/routes_abstract.py
bazis/contrib/users/schemas.py
bazis/contrib/users/service.py
bazis/contrib/users/locale/en/LC_MESSAGES/django.mo
bazis/contrib/users/locale/en/LC_MESSAGES/django.po
bazis/contrib/users/locale/ru/LC_MESSAGES/django.mo
bazis/contrib/users/locale/ru/LC_MESSAGES/django.po
bazis/contrib/users/migrations/0001_initial.py
bazis/contrib/users/migrations/0002_user_dt_first_login.py
bazis/contrib/users/migrations/__init__.py
bazis_users-2.2.0.dist-info/METADATA
bazis_users-2.2.0.dist-info/WHEEL
bazis_users-2.2.0.dist-info/top_level.txt
bazis_users-2.2.0.dist-info/RECORD
